pokete/__init__.py
pokete/__main__.py
pokete/release.py
pokete/assets/music/01 A Night Of Dizzy Spells.mp3
pokete/assets/music/02 Underclocked (underunderclocked mix).mp3
pokete/assets/music/03 Chibi Ninja.mp3
pokete/assets/music/04 All of Us.mp3
pokete/assets/music/05 Come and Find Me.mp3
pokete/assets/music/06 Searching.mp3
pokete/assets/music/07 We're the Resistors.mp3
pokete/assets/music/08 Ascending.mp3
pokete/assets/music/09 Come and Find Me - B mix.mp3
pokete/assets/music/10 Arpanauts.mp3
pokete/assets/music/11 HHavok-intro.mp3
pokete/assets/music/12 HHavok-main.mp3
pokete/assets/music/13 Digital Native.mp3
pokete/assets/music/14 Jumpshot.mp3
pokete/assets/music/15 Prologue.mp3
pokete/assets/music/16 We're all under the stars.mp3
pokete/assets/music/17 Behind the waterfall lies the beginning.mp3
pokete/assets/music/Map.mp3
pokete/assets/music/xDeviruchi - And The Journey Begins .mp3
pokete/assets/music/xDeviruchi - Decisive Battle (End).mp3
pokete/assets/music/xDeviruchi - Decisive Battle (Loop).mp3
pokete/assets/music/xDeviruchi - Exploring The Unknown.mp3
pokete/assets/music/xDeviruchi - Minigame .mp3
pokete/assets/music/xDeviruchi - Mysterious Dungeon.mp3
pokete/assets/music/xDeviruchi - Prepare for Battle! .mp3
pokete/assets/music/xDeviruchi - Take some rest and eat some food!.mp3
pokete/assets/music/xDeviruchi - The Final of The Fantasy.mp3
pokete/assets/music/xDeviruchi - The Icy Cave .mp3
pokete/assets/music/xDeviruchi - Title Theme .mp3
pokete/base/__init__.py
pokete/base/color.py
pokete/base/context.py
pokete/base/game_map.py
pokete/base/loops.py
pokete/base/periodic_event_manager.py
pokete/base/tss.py
pokete/base/exception_propagation/__init__.py
pokete/base/exception_propagation/exception_propagating_periodic_event.py
pokete/base/exception_propagation/propagating_thread.py
pokete/base/input/__init__.py
pokete/base/input/event.py
pokete/base/input/hotkeys.py
pokete/base/input/recogniser.py
pokete/base/input_loops/__init__.py
pokete-0.10.0rc4.dist-info/licenses/LICENSE
pokete-0.10.0rc4.dist-info/METADATA
pokete-0.10.0rc4.dist-info/WHEEL
pokete-0.10.0rc4.dist-info/entry_points.txt
pokete-0.10.0rc4.dist-info/top_level.txt
pokete-0.10.0rc4.dist-info/RECORD
