Metadata-Version: 2.4
Name: pokete
Version: 0.10.0rc4
Summary: A terminal based Pokemon like game
Author-email: lxgr <lxgr@protonmail.com>
License: GPL-3.0-only
Project-URL: Homepage, https://github.com/lxgr-linux/pokete
Project-URL: Issues, https://github.com/lxgr-linux/pokete/issue
Project-URL: Repository, https://github.com/lxgr-linux/pokete.git
Keywords: game,Ascii
Classifier: Programming Language :: Python :: 3
Classifier: Operating System :: OS Independent
Requires-Python: >=3.11
License-File: LICENSE
Requires-Dist: scrap_engine>=1.4.3
Dynamic: license-file
